fog_x/__init__.py
fog_x/__main__.py
fog_x/cli.py
fog_x/dataset.py
fog_x/episode.py
fog_x/feature.py
fog_x/database/__init__.py
fog_x/database/db_connector.py
fog_x/database/db_manager.py
fog_x/database/polars_connector.py
fog_x/database/utils.py
fog_x/rlds/__init__.py
fog_x/rlds/utils.py
fog_x/rlds/writer.py
fog_x/storage/__init__.py
fog_x/storage/storage.py
fog_x-0.1.0b4.dist-info/LICENSE
fog_x-0.1.0b4.dist-info/METADATA
fog_x-0.1.0b4.dist-info/WHEEL
fog_x-0.1.0b4.dist-info/top_level.txt
fog_x-0.1.0b4.dist-info/RECORD
