Metadata-Version: 2.1
Name: fog_x
Version: 0.1.0b4
Summary: An Efficient and Scalable Data Collection and Management Framework For Robotics Learning
License: 
Project-URL: homepage, https://github.com/BerkeleyAutomation/fog_x/
Keywords: robotics,data,management,collection,framework,learning
License-File: LICENSE
Requires-Dist: pandas
Requires-Dist: numpy
Requires-Dist: polars
Requires-Dist: pillow
Requires-Dist: pyarrow
Requires-Dist: opencv-python
Requires-Dist: sqlalchemy ==1.4.51
Requires-Dist: smart-open
Provides-Extra: all
Requires-Dist: datasets ; extra == 'all'
Requires-Dist: tensorflow ; extra == 'all'
Requires-Dist: tensorflow-datasets ; extra == 'all'
Requires-Dist: envlogger ; extra == 'all'
Requires-Dist: boto3 ; extra == 'all'
Requires-Dist: smart-open ; extra == 'all'
Requires-Dist: torch ; extra == 'all'
Requires-Dist: torchvision ; extra == 'all'
Provides-Extra: aws
Requires-Dist: boto3 ; extra == 'aws'
Provides-Extra: hf
Requires-Dist: datasets ; extra == 'hf'
Provides-Extra: rtx
Requires-Dist: tensorflow ; extra == 'rtx'
Requires-Dist: tensorflow-datasets ; extra == 'rtx'
Requires-Dist: envlogger ; extra == 'rtx'
Provides-Extra: torch
Requires-Dist: torch ; extra == 'torch'
